{
  "sent_keys": [
    "dcddb055ee2118ddee5004e2",
    "de3d686fdc512d1adf75550a"
  ],
  "alerts": [
    {
      "sent_at": "2026-06-03T14:05:33.055383+09:00",
      "key": "de3d686fdc512d1adf75550a",
      "title": "금융보안원 가입 GA 대폭 확대된다…'해킹 피해' 예방",
      "link": "https://www.etnews.com/20260602000349",
      "source": "etnews.com",
      "keyword": "인카금융"
    },
    {
      "sent_at": "2026-06-03T14:05:33.055383+09:00",
      "key": "dcddb055ee2118ddee5004e2",
      "title": "금융보안원 가입 GA 대폭 확대된다…'해킹 피해' 예방",
      "link": "https://www.etnews.com/20260602000349",
      "source": "etnews.com",
      "keyword": "인카금융"
    }
  ]
}